LICENSE
MANIFEST.in
README.md
setup.py
channelbindjs/__init__.py
channelbindjs/apps.py
channelbindjs.egg-info/PKG-INFO
channelbindjs.egg-info/SOURCES.txt
channelbindjs.egg-info/dependency_links.txt
channelbindjs.egg-info/requires.txt
channelbindjs.egg-info/top_level.txt
channelbindjs/static/channelbindjs/activate.js